{"indicator_number":"3.9.3","indicator_name":"Tasa de mortalidad atribuida a intoxicaciones involuntarias","national_indicator_description":"Tasa de mortalidad atribuida a intoxicaciones involuntarias","target_name":"By 2030, substantially reduce the number of deaths and illnesses from hazardous chemicals and air, water and soil pollution and contamination","goal_name":"Ensure healthy lives and promote well-being for all at all ages","computation_units":"Per 100,000 population","national_geographical_coverage":"Asturias","source_active_1":true,"source_organisation_1":"Estad\u00edstica de defunciones seg\u00fan la causa de muerte, INE","goal_meta_link":"https://unstats.un.org/sdgs/metadata/","goal_meta_link_text":"Nota metodol\u00f3gica del indicador 3.9.3.1","data_last_update":"06/05/2020","data_non_statistical":false,"reporting_status":"complete","graph_title":"Tasa de mortalidad atribuida a intoxicaciones involuntarias","graph_type":"line","national_data_update_url_text":"2020-11-24: see changes on GitHub","national_data_update_url":"https://github.com/sadeiasturias/asturias-datos/commit/c49870439de99baad5414307d039c263ab04799d","national_metadata_update_url_text":"2020-11-24: see changes on GitHub","national_metadata_update_url":"https://github.com/sadeiasturias/asturias-datos/commit/c49870439de99baad5414307d039c263ab04799d","page_content":"","indicator":"3.9.3.1","target_id":"3.9","sdg_goal":"3","indicator_sort_order":"03-09-03-01"}